Metadata-Version: 1.1
Name: virtualenvwrapper-sublime
Version: 0.0.7
Summary: It create sublime project file as creating new virtualenv using mkproject
Home-page: https://github.com/SongGithub/sublime_projectfile_maker
Author: Song Jin
Author-email: songjin@hotmail.com
License: UNKNOWN
Platform: Any
Classifier: Development Status :: 4 - Beta
Classifier: License :: OSI Approved :: BSD License
Classifier: Programming Language :: Python
Classifier: Intended Audience :: Developers
Classifier: Environment :: Console
Requires: virtualenv
Requires: virtualenvwrapper (>=2.0)
Provides: virtualenvwrapper.sublime
